time_cap/__init__.py
time_cap/time_cap.py
time_cap-0.0.4.dist-info/METADATA
time_cap-0.0.4.dist-info/WHEEL
time_cap-0.0.4.dist-info/licenses/LICENSE
time_cap-0.0.4.dist-info/RECORD
